ykenan_ukbiobank/__init__.py
ykenan_ukbiobank/download/__init__.py
ykenan_ukbiobank-0.0.16.dist-info/LICENSE
ykenan_ukbiobank-0.0.16.dist-info/METADATA
ykenan_ukbiobank-0.0.16.dist-info/WHEEL
ykenan_ukbiobank-0.0.16.dist-info/top_level.txt
ykenan_ukbiobank-0.0.16.dist-info/RECORD
