Metadata-Version: 2.1
Name: ykenan_ukbiobank
Version: 0.0.16
Summary: UK Biobank download
Author-email: Yu Zhengmin <3236170161@qq.com>
Project-URL: gitee, https://gitee.com/ykenan_yingying/ukbiobank
Keywords: YKenan,UK Biobank
Classifier: Programming Language :: Python :: 3
Classifier: License :: OSI Approved :: MIT License
Classifier: Operating System :: OS Independent
Requires-Python: >=3.10
License-File: LICENSE
Requires-Dist: setuptools >=42
Requires-Dist: numpy ==1.24.4
Requires-Dist: pandas ==2.0.3
Requires-Dist: ykenan-util ==0.0.5
Requires-Dist: ykenan-file ==0.2.3
